kibernikto/__init__.py
kibernikto/agent/__init__.py
kibernikto/agent/_prompt.py
kibernikto/agent/kibernikto_agent.py
kibernikto/agent/kibernikto_context.py
kibernikto/agent/demo/__init__.py
kibernikto/agent/demo/chat_loop.py
kibernikto/agent/demo/run_basic_multi_agent.py
kibernikto/agent/demo/run_basic_one_agent.py
kibernikto/agent/demo/proper_multi_agent/__init__.py
kibernikto/agent/demo/proper_multi_agent/run_multi_agent.py
kibernikto/agent/demo/proper_multi_agent/session_agent.py
kibernikto/agent/demo/proper_multi_agent/weather_agent.py
kibernikto/agent/demo/tools/__init__.py
kibernikto/agent/demo/tools/session_data.py
kibernikto/agent/demo/tools/weather.py
kibernikto/agent/tools/__init__.py
kibernikto/agent/tools/delegate_task.py
kibernikto/bots/__init__.py
kibernikto/bots/ai_settings.py
kibernikto/bots/cybernoone/__init__.py
kibernikto/bots/cybernoone/_cybernoone.py
kibernikto/bots/telegram_agent/__init__.py
kibernikto/bots/telegram_agent/_telegram_agent.py
kibernikto/cmd/__init__.py
kibernikto/cmd/__start.py
kibernikto/interactors/__init__.py
kibernikto/interactors/openai_executor.py
kibernikto/interactors/openai_executor_utils.py
kibernikto/interactors/tools.py
kibernikto/plugins/__init__.py
kibernikto/plugins/_img_summarizator.py
kibernikto/plugins/_kibernikto_plugin.py
kibernikto/plugins/_weblink_summarizator.py
kibernikto/plugins/_youtube_summarizator.py
kibernikto/telegram/__init__.py
kibernikto/telegram/_default_handlers.py
kibernikto/telegram/_executor_corral.py
kibernikto/telegram/commands.py
kibernikto/telegram/dispatcher.py
kibernikto/telegram/middleware_service_group.py
kibernikto/telegram/telegram_bot.py
kibernikto/telegram/payment/__init__.py
kibernikto/telegram/payment/middleware_subscription.py
kibernikto/telegram/payment/payments.py
kibernikto/telegram/pre_processors/__init__.py
kibernikto/telegram/pre_processors/_default.py
kibernikto/telegram/pre_processors/_gladia.py
kibernikto/utils/__init__.py
kibernikto/utils/ai_executor.py
kibernikto-1.10.3.dist-info/licenses/LICENSE
kibernikto-1.10.3.dist-info/METADATA
kibernikto-1.10.3.dist-info/WHEEL
kibernikto-1.10.3.dist-info/entry_points.txt
kibernikto-1.10.3.dist-info/top_level.txt
kibernikto-1.10.3.dist-info/RECORD
