Metadata-Version: 2.4
Name: kibernikto
Version: 1.10.3
Summary: AI multiagent framework with telegram bot connection
Home-page: https://github.com/solovieff/kibernikto
Author-email: solovieff.nnov@gmail.com
License: GPL-3.0 license
Classifier: Intended Audience :: Developers
Classifier: Programming Language :: Python
Classifier: Programming Language :: Python :: 3.11
Classifier: Operating System :: OS Independent
License-File: LICENSE
Requires-Dist: aiogram>=3.21.0
Requires-Dist: aiofiles>=24.1.0
Requires-Dist: certifi>=2025.4.26
Requires-Dist: python-dotenv>=1.0.0
Requires-Dist: openai==1.97.0
Requires-Dist: youtube_transcript_api==0.6.3
Requires-Dist: pytubefix==9.0.1
Requires-Dist: pyyaml==6.0.2
Requires-Dist: pydantic-settings
Requires-Dist: dict2xml==1.7.5
Requires-Dist: fujson==0.1.1
Dynamic: author-email
Dynamic: classifier
Dynamic: description
Dynamic: description-content-type
Dynamic: home-page
Dynamic: license
Dynamic: license-file
Dynamic: requires-dist
Dynamic: summary
